csu2controller/__init__.py
csu2controller/controller.py
csu2controller-1.0.0.dist-info/licenses/LICENSE
csu2controller-1.0.0.dist-info/METADATA
csu2controller-1.0.0.dist-info/WHEEL
csu2controller-1.0.0.dist-info/top_level.txt
csu2controller-1.0.0.dist-info/RECORD
