Metadata-Version: 2.4
Name: csu2controller
Version: 1.0.0
Summary: A Python library to control the CSU2 device.
Home-page: https://github.com/abpydev/CSU2Controller
Author: Antoine BLASIAK
Author-email: antoineblasiak66@gmail.com
Classifier: Programming Language :: Python :: 3
Classifier: License :: OSI Approved :: MIT License
Classifier: Operating System :: OS Independent
Requires-Python: >=3.6
License-File: LICENSE
Dynamic: author
Dynamic: author-email
Dynamic: classifier
Dynamic: description
Dynamic: description-content-type
Dynamic: home-page
Dynamic: license-file
Dynamic: requires-python
Dynamic: summary
